rslabel/__init__.py
rslabel/collect.py
rslabel/count.py
rslabel/delete.py
rslabel/get.py
rslabel/marker.py
rslabel/ret.py
rslabel/show.py
rslabel/stats.py
rslabel/upload.py
rslabel-0.9.1.data/scripts/rslabel
rslabel-0.9.1.dist-info/METADATA
rslabel-0.9.1.dist-info/RECORD
rslabel-0.9.1.dist-info/WHEEL
rslabel-0.9.1.dist-info/top_level.txt
