Metadata-Version: 2.1
Name: rslabel
Version: 0.9.1
Summary: Used for Palouse Robosub image labeling management.
Home-page: http://robosub.eecs.wsu.edu/wiki/cs/vision/image_tagging/start#data-management
Author: Ryan Summers
Author-email: summers.ryan.m@gmail.com
License: UNKNOWN
Platform: UNKNOWN
Requires-Dist: pysftp
Requires-Dist: progressbar2
